{
    "name": "The Wide, Wide World",
    "author": [
        "Warner, Susan"
    ],
    "body": "\n                    _The_ Pleasures of Literature\n                       and the Solace of Books\n\n                    COMPILED BY JOSEPH SHALER WITH\n                    AN INTRODUCTION BY ANDREW LANG\n\nA volume that will appeal to every book lover, presenting, as it does,\nin chaste and elegant style, the thoughts of great men of all ages on\nbooks and the reading thereof.\n\nA particularly dainty and appropriate gift for the reader or student,\nand one that is sure to be appreciated.\n\n_Printed on the finest deckle edge paper and bound in the best silk\nfinished cloth, with frontispiece and rubricated title page. Elaborate\ncover design in gold. Price, $1.00_\n\n\n\n                        Mrs. Jerningham's Journal\n                        John Jerningham's Journal\n\nThe re-publication of this exquisite love story inverse is an event that\nwill be heartily welcomed by those who can appreciate beauty of\nsentiment when presented in an unusual guise. No book is so appropriate\nfor a dainty and inexpensive wedding gift.\n\n_Two volumes, small 12mo in size, printed on the highest grade deckle\nedge paper and bound in light green cloth with ivory and gold\ndecorations. Encased in a flat box._\n\n_Price, $1.50 per set, postpaid._\n\n\n\n                        _Rubaiyat of Omar Khayyam_\n\nRendered into English verse by Edward Fitzgerald. A correct version of\nthe text of the Fourth Edition, with accurate notes, a biography of both\nOmar and Fitzgerald, and a Poetical Tribute by Andrew Lang, together\nwith a remarkable descriptive and comparative article by Edward S.\nHolden. Beautifully printed in two colors on deckel edge paper, with\ndecorative borders, fourteen half-tone illustrations by Gilbert James,\nand a portrait of Fitzgerald. Gilt tops, attractively bound in cloth and\ngold, and each volume encased in a flat box with cover. Size, 5-1/4 x\n7-5/8. PRICE, $1.25.\n\n_THE SAME_, small 12mo in size, handsomely bound in cloth and printed on\nthe finest deckle edge paper, with the fifteen illustrations in two\ncolors, and containing the same matter as the foregoing volume. PRICE,\n50c.\n\n_THE SAME_, in booklet form, 24 pages, printed in two colors, the\ncomplete text of the fourth edition. PRICE, 15c.\n\n\n\n_Kipling's Poems, Barrack Room Ballads, Departmental Ditties, etc._\n\nTwo volumes in one, with glossary. Fourteen full-page pen-and-ink\ndrawings together with a new portrait of the author. Handsomely bound in\ncloth, gilt tops, and printed on old Chester antique deckle edge paper.\nSize, 5-1/4 x 7-5/8 in., 340 pages. PRICE, $1.50.\n\n                _All books sent postpaid on receipt of price_\n\n\n\n          _No Field Collection is Complete Without this Book_\n\n                  A LITTLE BOOK _of_ TRIBUNE VERSE\n\n                          _By_ EUGENE FIELD\n\nCompiled and edited by JOSEPH G. BROWN, formerly city editor of the\n_Denver Tribune_, and an intimate friend and associate of the poet\nduring the several years in which he was on the staff of that paper.\n\nThis volume resurrects a literary treasure which has been buried for\nmany years in the forgotten files of a newspaper, and it is, as nearly\nas it has been possible to make, an absolutely complete collection of\nthe hitherto unpublished poems of the gifted author.\n\nThese poems are the early products of Field's genius. They breathe the\nspirit of Western life of twenty years ago. The reckless cowboy, the\nbucking broncho, the hardy miner, the English tenderfoot, the coquettish\nbelle, and all the foibles and extravagances of Western social life, are\ndepicted with a naivete and satire, tempered with sympathy and pathos,\nwhich no other writer could imitate.\n\nThe book contains nearly three hundred pages, including an interesting\nand valuable introduction by the editor, and is printed from new type on\nfine deckle edge paper, and handsomely bound in cloth, with gilt tops.\n\n                      _Retail price, 75 cents_\n\n                          GROSSET & DUNLAP\n                   *11 East 16th Street, NEW YORK*\n\n\n\n\n\n\nTranscriber's notes:\n\nAlternative spelling and hyphenation has been retained as it appears in\nthe original publication.\n\nAccented characters are represented within square brackets with the\ncorresponding accent, e.g. ['e] for e with acute, and [c,] for c with\ncedilla.",
    "metadata": {
        "author": [
            "Warner, Susan"
        ],
        "year": "Unknown",
        "url": "https://www.gutenberg.org/cache/epub/28376/pg28376.txt",
        "name": "the_wide_wide_world__warner.json"
    }
}